MetaTrader5/__init__.py
MetaTrader5/_core.cp314-win_amd64.pyd
metatrader5-5.0.5572.dist-info/licenses/LICENSE.txt
metatrader5-5.0.5572.dist-info/METADATA
metatrader5-5.0.5572.dist-info/WHEEL
metatrader5-5.0.5572.dist-info/top_level.txt
metatrader5-5.0.5572.dist-info/RECORD
