Metadata-Version: 2.4
Name: metatrader5
Version: 5.0.5572
Summary: API Connector to MetaTrader 5 Terminal
Home-page: https://www.metatrader5.com
Author: MetaQuotes Ltd.
Author-email: plugins@metaquotes.net
Maintainer: MetaQuotes Ltd.
Maintainer-email: plugins@metaquotes.net
License: MIT
Project-URL: Documentation, https://www.mql5.com/en/docs/integration/python_metatrader5
Project-URL: Forum, https://www.mql5.com/en/forum
Keywords: metatrader mt5 metaquotes mql5 forex currency exchange
Platform: Windows
Classifier: Development Status :: 5 - Production/Stable
Classifier: Topic :: Office/Business :: Financial
Classifier: License :: OSI Approved :: MIT License
Classifier: Programming Language :: Python :: 3
Classifier: Programming Language :: Python :: 3.6
Classifier: Programming Language :: Python :: 3.7
Classifier: Programming Language :: Python :: 3.8
Classifier: Programming Language :: Python :: 3.9
Classifier: Programming Language :: Python :: 3.10
Classifier: Programming Language :: Python :: 3.11
Classifier: Programming Language :: Python :: 3.12
Classifier: Programming Language :: Python :: 3.13
Classifier: Programming Language :: Python :: 3.14
Requires-Python: >=3.6,<4
License-File: LICENSE.txt
Requires-Dist: numpy>=1.7
Dynamic: author
Dynamic: author-email
Dynamic: classifier
Dynamic: description
Dynamic: description-content-type
Dynamic: home-page
Dynamic: keywords
Dynamic: license
Dynamic: license-file
Dynamic: maintainer
Dynamic: maintainer-email
Dynamic: platform
Dynamic: project-url
Dynamic: requires-dist
Dynamic: requires-python
Dynamic: summary
